spicy/__init__.py
spicy/dom/__init__.py
spicy/dom/base/__init__.py
spicy/dom/base/attribute.py
spicy/dom/base/document.py
spicy/dom/base/tag.py
spicy/dom/html/__init__.py
spicy/dom/html/document.py
spicy/dom/html/enum_.py
spicy/dom/html/tag.py
spicy/dom/xml/__init__.py
spicy/dom/xml/document.py
spicy/dom/xml/enum_.py
spicy/dom/xml/tag.py
spicy/tree/__init__.py
spicy/tree/base.py
spicy/tree/tree.py
spicy/utils/__init__.py
spicy/utils/config.py
spicy/utils/exceptions.py
tests/test_html/__init__.py
tests/test_html/test_html.py
spicyy-0.6.dist-info/LICENSE
spicyy-0.6.dist-info/METADATA
spicyy-0.6.dist-info/WHEEL
spicyy-0.6.dist-info/top_level.txt
spicyy-0.6.dist-info/RECORD
