Metadata-Version: 2.1
Name: spicyy
Version: 0.6
Summary: DOM parser for html, xml and other.
Home-page: https://github.com/michael7nightingale/spicy
Author: Michael Nightingale
Author-email: suslanchikmopl@gmail.com
License: MIT
Platform: UNKNOWN
License-File: LICENSE
